vsrc/sccb_fsm.v
//////////////////////////////////////////////////////////////////////////////////
// Company: Private
// Engineer: JunkaiZhan
// 
// Create Date: 2018-12-17
// Design Name: Image Recognition
// Module Name: sccb fsm for sccb interface driver for dcmi (for ov7725)
// Target Devices: ASIC/FPGA
// Tool Version: 
// Description: 
//      Like IIC interface
// Dependencies: 
// 
// Revision: 
// Revision 0.01 - File Created
//
// //////////////////////////////////////////////////////////////////////////////////
`timescale 1ns/1ps

`define SEQ_LENGTH   24;
`define STATE_WIDTH  5;

module sccb_fsm(
    clk, rstn, 
    valid_in, write, data_in, addr, 
    done, data_out,
    scl, sda,
    direction // for debug
);

// Parameter Declarations --------------------------------------
parameter DATA_WIDTH = 8;
parameter ADDR_WIDTH = 8;

parameter BYTE_COUNT_WIDTH = 2;
parameter BIT_COUNT_WIDTH  = 4;

localparam IDLE      = 5'h0;
localparam START     = 5'd1;
localparam TRA_0     = 5'd2;
localparam TRA_1     = 5'd3;
localparam TRA_2     = 5'd4;
localparam TRA_3     = 5'd5;
localparam ACK_1     = 5'd6;
localparam ACK_2     = 5'd7;
localparam ACK_3     = 5'd8;
localparam REC_1     = 5'd9;
localparam REC_2     = 5'd10;
localparam PER_ACK_1 = 5'd11;
localparam PER_ACK_2 = 5'd12;
localparam PER_ACK_3 = 5'd13;
localparam PER_ACK_4 = 5'd14;
localparam STOP_1    = 5'd15;
localparam STOP_2    = 5'd16;
localparam STOP_3    = 5'd17;

localparam DEVICE_ADDRESS = 7'h42;

// Interface Declarations --------------------------------------
input clk, rstn;
input valid_in, write;
input [DATA_WIDTH - 1 : 0] data_in;
input [ADDR_WIDTH - 1 : 0] addr;
output [DATA_WIDTH - 1 : 0] data_out;
output done;

output scl;
inout  sda;

output direction; // for debug

// inout process
wire in_sda;
reg out_sda, sda_out_en;
assign in_sda = !sda_out_en & sda;
assign sda = sda_out_en ? out_sda : 1'bz;

reg scl_r;
assign scl = scl_r;

assign direction = sda_out_en; // for debug

// Reg and Wire Declarations -----------------------------------
reg [5 - 1 : 0] state;
reg [5 - 1 : 0] next_state;

reg [BYTE_COUNT_WIDTH - 1 : 0] byte_counter;
reg [BIT_COUNT_WIDTH - 1 : 0] bit_counter;
reg [24 - 1 : 0] seq;

reg ack_valid;
reg [DATA_WIDTH - 1 : 0] data_receive;
reg [2:0] rec_counter;

// output data process
assign done = state == STOP_3; // one pluse
assign data_out = data_receive;

wire rec_finish;
assign rec_finish = &rec_counter;

wire valid_bit;
assign valid_bit = seq[24 - 1];

wire byte_counter_is_zero;
wire bit_counter_is_zero;
assign byte_counter_is_zero = ~|byte_counter;
assign bit_counter_is_zero  = ~|bit_counter;

reg read_command;
reg write_command;

// Seq Logic ---------------------------------------------------
always @ (posedge clk or negedge rstn) begin
    if(!rstn) state <= IDLE;
    else state <= next_state;
end

always @ (*) begin
    case(state)
    IDLE: begin 
        if(read_command || write_command) next_state = START;
        else next_state = IDLE;
    end
    START: begin next_state = TRA_0; end
    TRA_0: begin next_state = TRA_1; end
    TRA_1: begin next_state = TRA_2; end
    TRA_2: begin next_state = TRA_3; end
    TRA_3: begin 
        if(bit_counter_is_zero) next_state = ACK_1;
        else next_state = TRA_0;
    end
    ACK_1: begin next_state = ACK_2; end
    ACK_2: begin next_state = ACK_3; end
    ACK_3: begin
        if(ack_valid) begin
            case(byte_counter)
            2: begin next_state = TRA_0; end
            1: begin
                if(read_command) next_state = START;
                else if(write_command) next_state = TRA_0;
            end 
            0: begin
                if(read_command) next_state = REC_1;
                else if(write_command) next_state = STOP_1;
            end
            default: next_state = TRA_0;
            endcase
        end else begin 
            next_state = STOP_1;
        end
    end
    REC_1: begin next_state = REC_2; end
    REC_2: begin 
        if(rec_finish) next_state = PER_ACK_1;
        else next_state = REC_1; 
    end
    PER_ACK_1: begin next_state = PER_ACK_2; end
    PER_ACK_2: begin next_state = PER_ACK_3; end
    PER_ACK_3: begin next_state = PER_ACK_4; end
    PER_ACK_4: begin next_state = STOP_1;    end
    STOP_1:    begin next_state = STOP_2;    end
    STOP_2:    begin next_state = STOP_3;    end
    STOP_3:    begin next_state = IDLE;      end
    endcase
end

always @ (*) begin
    case(state)
    IDLE:      begin scl_r = 1; sda_out_en = 1; out_sda = 1; end
    START:     begin scl_r = 1; sda_out_en = 1; out_sda = 0; end
    TRA_0:     begin scl_r = 0; sda_out_en = 1; end
    TRA_1:     begin scl_r = 0; sda_out_en = 1; out_sda = valid_bit; end
    TRA_2:     begin scl_r = 1; sda_out_en = 1; out_sda = valid_bit; end
    TRA_3:     begin scl_r = 0; sda_out_en = 1; out_sda = valid_bit; end
    ACK_1:     begin scl_r = 0; sda_out_en = 0; end
    ACK_2:     begin scl_r = 1; sda_out_en = 0; end
    ACK_3:     begin scl_r = 0; sda_out_en = 0; end
    REC_1:     begin scl_r = 0; sda_out_en = 0; end
    REC_2:     begin scl_r = 1; sda_out_en = 0; end
    PER_ACK_1: begin scl_r = 0; sda_out_en = 1; end
    PER_ACK_2: begin scl_r = 0; sda_out_en = 1; out_sda = 0; end
    PER_ACK_3: begin scl_r = 1; sda_out_en = 1; out_sda = 0; end
    PER_ACK_4: begin scl_r = 0; sda_out_en = 1; out_sda = 0; end
    STOP_1:    begin scl_r = 0; sda_out_en = 1; out_sda = 0; end
    STOP_2:    begin scl_r = 1; sda_out_en = 1; out_sda = 0; end
    STOP_3:    begin scl_r = 1; sda_out_en = 1; out_sda = 1; end
    default:   begin scl_r = 1; sda_out_en = 1; out_sda = 1; end
    endcase
end

// counter driver
always @ (posedge clk or negedge rstn) begin
    if(!rstn) begin
        byte_counter <= 0;
        bit_counter  <= 0;
    end else begin
        if(state == TRA_0) begin
            if(!bit_counter_is_zero) begin 
                bit_counter <= bit_counter - 1'b1; 
            end else if(!byte_counter_is_zero) begin 
                bit_counter <= 8; 
                byte_counter <= byte_counter - 1'b1; 
            end
        end else if(valid_in) begin 
            byte_counter <= 3;
            bit_counter  <= 8;
        end
    end
end

// address + data driver
always @ (posedge clk or negedge rstn) begin
    if(!rstn) begin
        seq <= 'd0;
    end else begin
        if(state == IDLE && write_command) begin
            seq <= {DEVICE_ADDRESS, 1'b0, addr, data_in};
        end else if(state == IDLE && read_command) begin
            seq <= {DEVICE_ADDRESS, 1'b0, addr, DEVICE_ADDRESS, 1'b1};
        end else if(state == TRA_3) begin
            seq <= seq << 1;
        end
    end
end

// ack_valid driver
always @ (posedge clk or negedge rstn) begin
    if(!rstn) begin
        ack_valid <= 1'b0;
    end else begin
        if(state == ACK_1) ack_valid <= !in_sda;
        else ack_valid <= 1'b0;
    end
end

// data receive driver
always @ (posedge clk or negedge rstn) begin
    if(!rstn) begin
        data_receive <= 'b0;
        rec_counter <= 'b0;
    end else begin
        if(state == REC_1) begin
            data_receive <= {data_receive[DATA_WIDTH - 2 : 0], in_sda};
            rec_counter <= rec_counter + 1'b1;
        end else if(done) begin
            rec_counter <= 'b0;
        end
    end
end

// read_command and write_command driver
always @ (posedge clk or negedge rstn) begin
    if(!rstn) begin
        read_command <= 1'b0;
        write_command <= 1'b0;
    end else begin
        if(valid_in) begin
            write_command <= !write;
            read_command <= write;
        end else if(done) begin
            write_command <= 1'b0;
            read_command <= 1'b0;
        end
    end
end

endmodule

vsrc/sccb.v
//////////////////////////////////////////////////////////////////////////////////
// Company: Private
// Engineer: JunkaiZhan
// 
// Create Date: 2018-12-17
// Design Name: Image Recognition
// Module Name: sccb interface driver for dcmi (for ov7725)
// Target Devices: ASIC/FPGA
// Tool Version: 
// Description: 
//      Like IIC interface, the internal interface is like AHB
// Dependencies: 
// 
// Revision: 
// Revision 0.01 - File Created
//
// //////////////////////////////////////////////////////////////////////////////////
`timescale 1ns/1ps

module sccb (
    clk, rstn, 
    scl, sda, 
    data_in, data_out, 
    addr, write, 
    valid_in, done,
    direction
);

// Parameter Declarations -------------------------------------
parameter DATA_WIDTH = 8;
parameter ADDR_WIDTH = 8;

// Interface Declarations -------------------------------------
input clk;
input rstn;

// sccb interface
output scl;
inout  sda;

// internal interface
input  [DATA_WIDTH - 1 : 0] data_in;
input  [ADDR_WIDTH - 1 : 0] addr;     // address to wirte or read
input  write;                         // 1 - write, 0 - read
input  valid_in;
output [DATA_WIDTH - 1 : 0] data_out; 
output done;

output direction; // for debug

// Reg and Wire Declarations ----------------------------------
// capture registers
reg [DATA_WIDTH - 1 : 0] data_in_r;
reg [ADDR_WIDTH - 1 : 0] addr_r;
reg write_r;

// handshake signals
reg ready;

// Seq Logic --------------------------------------------------
always @ (posedge clk or negedge rstn) begin
    if(!rstn) begin
        data_in_r <= 'b0;
        addr_r <= 'b0;
        write_r <= 'b0;
    end else begin
        if(valid_in == 1'b1 && ready == 1'b1) begin
            data_in_r <= data_in;
            addr_r <= addr;
            write_r <= write;
        end 
    end
end

always @ (posedge clk or negedge rstn) begin
    if(!rstn) ready <= 1'b1; 
    else begin
        if(valid_in == 1'b1) ready <= 1'b0;
        else if(done == 1'b1) ready <= 1'b1;
    end
end

// Sub Module Declarations ------------------------------------
sccb_fsm sccb_fsm(
    .clk(clk),
    .rstn(rstn),
    .valid_in(valid_in),
    .write(write_r),
    .data_in(data_in_r),
    .addr(addr_r),
    .done(done),
    .data_out(data_out),
    .scl(scl),
    .sda(sda),
    .direction(direction) // for debug
);

endmodule

testbench/sccb_tb.v
//////////////////////////////////////////////////////////////////////////////////
// Company: Private
// Engineer: JunkaiZhan
// 
// Create Date: 2018-12-17
// Design Name: Image Recognition
// Module Name: sccb interface driver for dcmi (for ov7725)
// Target Devices: ASIC/FPGA
// Tool Version: 
// Description: 
//      Testbench
// Dependencies: 
//      sccb.v
// Revision: 
// Revision 0.01 - File Created
//
////////////////////////////////////////////////////////////////////////////////////
`timescale 1ns/1ps

module sccb_tb();

// Parameter Declarations 
parameter DATA_WIDTH = 8;
parameter ADDR_WIDTH = 8;
parameter time_cycle = 10;

// Interface Declaration
reg clk, rstn;
reg [DATA_WIDTH - 1 : 0] data_in;
reg [ADDR_WIDTH - 1 : 0] addr;     // address to wirte or read
reg write;                         // 1 - write, 0 - read
reg valid_in;

wire sda, direction;
reg sda_out;
assign sda = direction ? sda_out : 1'bz;

wire scl;
wire [DATA_WIDTH - 1 : 0] data_out; 
wire done; 

// Design Under Test
sccb dut(
    .clk(clk),
    .rstn(rstn),
    .data_in(data_in),
    .addr(addr),
    .write(write),
    .valid_in(valid_in),
    .sda(sda),
    .scl(scl),
    .data_out(data_out),
    .done(done),
    .direction(direction)
);

// clock and reset_n
initial begin
    clk = 1;
    rstn = 1;
    #(time_cycle*2) rstn = 0;
    #(time_cycle*2) rstn = 1;
end

always begin
    #(time_cycle/2) clk = ~clk;
end

// dump out file and variables
initial begin
    $dumpfile("sccb_wv.vcd");
    $dumpvars(0, dut);
end

// logic
initial begin
    data_in = 0;
    addr = 0;
    write = 0;
    valid_in = 0;
    sda_out = 1;
    #(time_cycle*6);

    data_in = 8'h5b;
    addr = 8'ha6;
    write = 0;
    sda_out = 1;
    valid_in = 1;
    #time_cycle;
    data_in = 8'h5b;
    addr = 8'ha6;
    write = 0;
    valid_in = 0;
    sda_out = 1;
    #(time_cycle*200);

    data_in = 8'h73;
    addr = 8'h95;
    write = 0;
    valid_in = 1;
    sda_out = 1;
    #time_cycle;
    data_in = 8'h73;
    addr = 8'h95;
    write = 0;
    valid_in = 0;
    sda_out = 1;
    #(time_cycle*200);

    data_in = 8'h5b;
    addr = 8'ha6;
    write = 1;
    valid_in = 1;
    sda_out = 1;
    #time_cycle;
    data_in = 8'h5b;
    addr = 8'ha6;
    write = 1;
    valid_in = 0;
    sda_out = 1;
    #(time_cycle*200);

    data_in = 8'h73;
    addr = 8'h95;
    write = 1;
    valid_in = 1;
    sda_out = 1;
    #time_cycle;
    data_in = 8'h73;
    addr = 8'h95;
    write = 1;
    valid_in = 0;
    sda_out = 1;
    #(time_cycle*200);

    #(time_cycle*100);
    $finish;
end

endmodule

sccb_wv.vcd
$date
	Wed Dec 19 21:09:08 2018
$end
$version
	Icarus Verilog
$end
$timescale
	1ps
$end
$scope module sccb_tb $end
$scope module dut $end
$var wire 8 ! addr [7:0] $end
$var wire 1 " clk $end
$var wire 8 # data_in [7:0] $end
$var wire 1 $ rstn $end
$var wire 1 % sda $end
$var wire 1 & valid_in $end
$var wire 1 ' write $end
$var wire 1 ( scl $end
$var wire 1 ) done $end
$var wire 1 * direction $end
$var wire 8 + data_out [7:0] $end
$var reg 8 , addr_r [7:0] $end
$var reg 8 - data_in_r [7:0] $end
$var reg 1 . ready $end
$var reg 1 / write_r $end
$scope module sccb_fsm $end
$var wire 8 0 addr [7:0] $end
$var wire 1 " clk $end
$var wire 8 1 data_in [7:0] $end
$var wire 8 2 data_out [7:0] $end
$var wire 1 * direction $end
$var wire 1 3 in_sda $end
$var wire 1 $ rstn $end
$var wire 1 ( scl $end
$var wire 1 % sda $end
$var wire 1 & valid_in $end
$var wire 1 / write $end
$var wire 1 4 valid_bit $end
$var wire 1 5 rec_finish $end
$var wire 1 ) done $end
$var wire 1 6 byte_counter_is_zero $end
$var wire 1 7 bit_counter_is_zero $end
$var reg 1 8 ack_valid $end
$var reg 4 9 bit_counter [3:0] $end
$var reg 2 : byte_counter [1:0] $end
$var reg 8 ; data_receive [7:0] $end
$var reg 5 < next_state [4:0] $end
$var reg 1 = out_sda $end
$var reg 1 > read_command $end
$var reg 3 ? rec_counter [2:0] $end
$var reg 1 @ scl_r $end
$var reg 1 A sda_out_en $end
$var reg 24 B seq [23:0] $end
$var reg 5 C state [4:0] $end
$var reg 1 D write_command $end
$upscope $end
$upscope $end
$upscope $end
$enddefinitions $end
#0
$dumpvars
xD
bx C
bx B
xA
x@
bx ?
x>
x=
bx <
bx ;
bx :
bx 9
08
x7
x6
x5
x4
x3
bx 2
bx 1
bx 0
x/
x.
bx -
bx ,
bx +
x*
x)
x(
0'
0&
x%
1$
b0 #
1"
b0 !
$end
#5000
0"
#10000
1"
#15000
0"
#20000
03
1%
1=
1*
1A
1(
1@
04
b0 <
0)
b0 C
17
b0 9
16
b0 :
b0 B
05
b0 ?
b0 +
b0 2
b0 ;
0D
0>
0/
b0 ,
b0 0
b0 -
b0 1
1.
1"
0$
#25000
0"
#30000
1"
#35000
0"
#40000
1"
1$
#45000
0"
#50000
1"
#55000
0"
#60000
b1 <
07
b1000 9
06
b11 :
1D
b10100110 ,
b10100110 0
b1011011 -
b1011011 1
0.
1"
1&
b10100110 !
b1011011 #
#65000
0"
#70000
x%
14
0=
b10 <
b100001001010011001011011 B
b1 C
1"
0&
#75000
0"
#80000
0(
0@
b11 <
b10 C
1"
#85000
0"
#90000
1%
1=
b100 <
b111 9
b11 C
1"
#95000
0"
#100000
1(
1@
b101 <
b100 C
1"
#105000
0"
#110000
0(
0@
b10 <
b101 C
1"
#115000
0"
#120000
b11 <
04
b10 C
b10010100110010110110 B
1"
#125000
0"
#130000
x%
0=
b100 <
b110 9
b11 C
1"
#135000
0"
#140000
1(
1@
b101 <
b100 C
1"
#145000
0"
#150000
0(
0@
b10 <
b101 C
1"
#155000
0"
#160000
b11 <
b10 C
b100101001100101101100 B
1"
#165000
0"
#170000
b100 <
b101 9
b11 C
1"
#175000
0"
#180000
1(
1@
b101 <
b100 C
1"
#185000
0"
#190000
0(
0@
b10 <
b101 C
1"
#195000
0"
#200000
b11 <
b10 C
b1001010011001011011000 B
1"
#205000
0"
#210000
b100 <
b100 9
b11 C
1"
#215000
0"
#220000
1(
1@
b101 <
b100 C
1"
#225000
0"
#230000
0(
0@
b10 <
b101 C
1"
#235000
0"
#240000
b11 <
b10 C
b10010100110010110110000 B
1"
#245000
0"
#250000
b100 <
b11 9
b11 C
1"
#255000
0"
#260000
1(
1@
b101 <
b100 C
1"
#265000
0"
#270000
0(
0@
b10 <
b101 C
1"
#275000
0"
#280000
b11 <
14
b10 C
b100101001100101101100000 B
1"
#285000
0"
#290000
1%
1=
b100 <
b10 9
b11 C
1"
#295000
0"
#300000
1(
1@
b101 <
b100 C
1"
#305000
0"
#310000
0(
0@
b10 <
b101 C
1"
#315000
0"
#320000
b11 <
04
b10 C
b1010011001011011000000 B
1"
#325000
0"
#330000
x%
0=
b100 <
b1 9
b11 C
1"
#335000
0"
#340000
1(
1@
b101 <
b100 C
1"
#345000
0"
#350000
0(
0@
b10 <
b101 C
1"
#355000
0"
#360000
b11 <
b10 C
b10100110010110110000000 B
1"
#365000
0"
#370000
b100 <
17
b0 9
b11 C
1"
#375000
0"
#380000
1(
1@
b101 <
b100 C
1"
#385000
0"
#390000
0(
0@
b110 <
b101 C
1"
#395000
0"
#400000
x3
z%
0*
0A
b111 <
14
b110 C
b101001100101101100000000 B
1"
#405000
0"
#410000
1(
1@
b1000 <
x8
b111 C
1"
#415000
0"
#420000
0(
0@
b1111 <
b1000 C
08
1"
#425000
0"
#430000
03
x%
1*
1A
b10000 <
b1111 C
1"
#435000
0"
#440000
1(
1@
b10001 <
b10000 C
1"
#445000
0"
#450000
1%
1=
b0 <
1)
b10001 C
1"
#455000
0"
#460000
0)
b0 C
0D
1.
1"
