vsrc/sccb_fsm.v
//////////////////////////////////////////////////////////////////////////////////
// Company: Private
// Engineer: JunkaiZhan
// 
// Create Date: 2018-12-17
// Design Name: Image Recognition
// Module Name: sccb fsm for sccb interface driver for dcmi (for ov7725)
// Target Devices: ASIC/FPGA
// Tool Version: 
// Description: 
//      Like IIC interface
// Dependencies: 
// 
// Revision: 
// Revision 0.01 - File Created
//
// //////////////////////////////////////////////////////////////////////////////////
`timescale 1ns/1ps

`define SEQ_LENGTH   24;
`define STATE_WIDTH  5;

module sccb_fsm(
    clk, rstn, 
    valid_in, write, 
    data_in, addr, 
    done, data_out,
    scl, sda,
    direction // for debug
);

// Parameter Declarations --------------------------------------
parameter DATA_WIDTH = 8;
parameter ADDR_WIDTH = 8;

parameter BYTE_COUNT_WIDTH = 2;
parameter BIT_COUNT_WIDTH  = 4;

localparam IDLE      = 5'h0;
localparam START_1   = 5'd1;
localparam START_2   = 5'd2;
localparam TRA_1     = 5'd3;
localparam TRA_2     = 5'd4;
localparam TRA_3     = 5'd5;
localparam ACK_1     = 5'd6;
localparam ACK_2     = 5'd7;
localparam ACK_3     = 5'd8;
localparam REC_1     = 5'd9;
localparam REC_2     = 5'd10;
localparam REC_3     = 5'd11;
localparam PER_ACK_1 = 5'd12;
localparam PER_ACK_2 = 5'd13;
localparam PER_ACK_3 = 5'd14;
localparam STOP_1    = 5'd15;
localparam STOP_2    = 5'd16;
localparam STOP_3    = 5'd17;
localparam START_00  = 5'd18; // restart
localparam START_01  = 5'd19;
localparam START_02  = 5'd20;
localparam START_03  = 5'd21;

localparam DEVICE_ADDRESS = 7'h42;

// Interface Declarations --------------------------------------
input clk, rstn;
input valid_in, write;
input [DATA_WIDTH - 1 : 0] data_in;
input [ADDR_WIDTH - 1 : 0] addr;
output [DATA_WIDTH - 1 : 0] data_out;
output done;

output scl;
inout  sda;

output direction; // for debug

// inout process
wire in_sda;
reg out_sda, sda_out_en;
assign in_sda = !sda_out_en & sda;
assign sda = sda_out_en ? out_sda : 1'bz;

reg scl_r;
assign scl = scl_r;

assign direction = sda_out_en; // for debug

// Reg and Wire Declarations -----------------------------------
reg [5 - 1 : 0] state;
reg [5 - 1 : 0] next_state;

reg [BYTE_COUNT_WIDTH - 1 : 0] byte_counter;
reg [BIT_COUNT_WIDTH - 1 : 0] bit_counter;
reg [24 - 1 : 0] seq;

reg ack_valid;
reg [DATA_WIDTH - 1 : 0] data_receive;
reg [3:0] rec_counter;

// output data process
assign done = state == STOP_3; // one pluse
assign data_out = data_receive;

wire rec_finish;
assign rec_finish = rec_counter == 4'd8;

wire valid_bit;
assign valid_bit = seq[24 - 1];

wire byte_counter_is_zero;
wire bit_counter_is_zero;
assign byte_counter_is_zero = ~|byte_counter;
assign bit_counter_is_zero  = ~|bit_counter;

reg read_command;
reg write_command;

// Seq Logic ---------------------------------------------------
always @ (posedge clk or negedge rstn) begin
    if(!rstn) state <= IDLE;
    else state <= next_state;
end

always @ (*) begin
    case(state)
    IDLE: begin 
        if(read_command || write_command) next_state = START_1;
        else next_state = IDLE;
    end
    START_00: begin next_state = START_01; end
    START_01: begin next_state = START_02; end
    START_02: begin next_state = START_03; end
    START_03: begin next_state = START_1; end
    START_1: begin next_state = START_2; end
    START_2: begin next_state = TRA_1; end
    TRA_1: begin next_state = TRA_2; end
    TRA_2: begin next_state = TRA_3; end
    TRA_3: begin 
        if(bit_counter_is_zero) next_state = ACK_1;
        else next_state = TRA_1;
    end
    ACK_1: begin next_state = ACK_2; end
    ACK_2: begin next_state = ACK_3; end
    ACK_3: begin
        if(ack_valid) begin
            case(byte_counter)
            2: begin next_state = TRA_1; end
            1: begin
                if(read_command) next_state = START_00;
                else if(write_command) next_state = TRA_1;
            end 
            0: begin
                if(read_command) next_state = REC_1;
                else if(write_command) next_state = STOP_1;
            end
            default: next_state = TRA_1;
            endcase
        end else begin 
            next_state = STOP_1;
        end
    end
    REC_1: begin next_state = REC_2; end
    REC_2: begin next_state = REC_3; end
    REC_3: begin 
        if(rec_finish) next_state = PER_ACK_1;
        else next_state = REC_1; 
    end
    PER_ACK_1: begin next_state = PER_ACK_2; end
    PER_ACK_2: begin next_state = PER_ACK_3; end
    PER_ACK_3: begin next_state = STOP_1;    end
    STOP_1:    begin next_state = STOP_2;    end
    STOP_2:    begin next_state = STOP_3;    end
    STOP_3:    begin next_state = IDLE;      end
    endcase
end

always @ (*) begin
    case(state)
    IDLE:      begin scl_r = 1; sda_out_en = 1; out_sda = 1; end
    START_00:  begin scl_r = 0; sda_out_en = 1; out_sda = 0; end
    START_01:  begin scl_r = 1; sda_out_en = 1; out_sda = 0; end
    START_02:  begin scl_r = 1; sda_out_en = 1; out_sda = 1; end
    START_03:  begin scl_r = 1; sda_out_en = 1; out_sda = 1; end
    START_1:   begin scl_r = 1; sda_out_en = 1; out_sda = 0; end
    START_2:   begin scl_r = 0; sda_out_en = 1; out_sda = 0; end
    TRA_1:     begin scl_r = 0; sda_out_en = 1; out_sda = valid_bit; end
    TRA_2:     begin scl_r = 1; sda_out_en = 1; out_sda = valid_bit; end
    TRA_3:     begin scl_r = 0; sda_out_en = 1; out_sda = valid_bit; end
    ACK_1:     begin scl_r = 0; sda_out_en = 0; end
    ACK_2:     begin scl_r = 1; sda_out_en = 0; end
    ACK_3:     begin scl_r = 0; sda_out_en = 0; end
    REC_1:     begin scl_r = 0; sda_out_en = 0; end
    REC_2:     begin scl_r = 1; sda_out_en = 0; end
    REC_3:     begin scl_r = 0; sda_out_en = 0; end
    PER_ACK_1: begin scl_r = 0; sda_out_en = 1; out_sda = 0; end
    PER_ACK_2: begin scl_r = 1; sda_out_en = 1; out_sda = 0; end
    PER_ACK_3: begin scl_r = 0; sda_out_en = 1; out_sda = 0; end
    STOP_1:    begin scl_r = 0; sda_out_en = 1; out_sda = 0; end
    STOP_2:    begin scl_r = 1; sda_out_en = 1; out_sda = 0; end
    STOP_3:    begin scl_r = 1; sda_out_en = 1; out_sda = 1; end
    default:   begin scl_r = 1; sda_out_en = 1; out_sda = 1; end
    endcase
end

// counter driver
always @ (posedge clk or negedge rstn) begin
    if(!rstn) begin
        byte_counter <= 0;
        bit_counter  <= 0;
    end else begin
        if(state == TRA_1) begin
            if(!bit_counter_is_zero) begin 
                bit_counter <= bit_counter - 1'b1; 
            end else if(!byte_counter_is_zero) begin 
                bit_counter <= 7; 
                byte_counter <= byte_counter - 1'b1; 
            end
        end else if(valid_in) begin 
            byte_counter <= 2;
            bit_counter  <= 8;
        end
    end
end

// address + data driver
always @ (posedge clk or negedge rstn) begin
    if(!rstn) begin
        seq <= 'd0;
    end else begin
        if(state == IDLE && write_command) begin
            seq <= {DEVICE_ADDRESS, 1'b0, addr, data_in};
        end else if(state == IDLE && read_command) begin
            seq <= {DEVICE_ADDRESS, 1'b0, addr, DEVICE_ADDRESS, 1'b1};
        end else if(state == TRA_3) begin
            seq <= seq << 1;
        end
    end
end

// ack_valid driver
always @ (posedge clk or negedge rstn) begin
    if(!rstn) begin
        ack_valid <= 1'b0;
    end else begin
        if(state == ACK_1) ack_valid <= !in_sda;
    end
end

// data receive driver
always @ (posedge clk or negedge rstn) begin
    if(!rstn) begin
        data_receive <= 'b0;
        rec_counter <= 'b0;
    end else begin
        if(state == REC_1) begin
            data_receive <= {data_receive[DATA_WIDTH - 2 : 0], in_sda};
            rec_counter <= rec_counter + 1'b1;
        end else if(done) begin
            rec_counter <= 'b0;
        end
    end
end

// read_command and write_command driver
always @ (posedge clk or negedge rstn) begin
    if(!rstn) begin
        read_command <= 1'b0;
        write_command <= 1'b0;
    end else begin
        if(valid_in) begin
            write_command <= !write;
            read_command <= write;
        end else if(done) begin
            write_command <= 1'b0;
            read_command <= 1'b0;
        end
    end
end

endmodule

vsrc/sccb.v
//////////////////////////////////////////////////////////////////////////////////
// Company: Private
// Engineer: JunkaiZhan
// 
// Create Date: 2018-12-17
// Design Name: Image Recognition
// Module Name: sccb interface driver for dcmi (for ov7725)
// Target Devices: ASIC/FPGA
// Tool Version: 
// Description: 
//      Like IIC interface, the internal interface is like AHB
// Dependencies: 
// 
// Revision: 
// Revision 0.01 - File Created
//
// //////////////////////////////////////////////////////////////////////////////////
`timescale 1ns/1ps

module sccb (
    clk, rstn, 
    scl, sda, 
    data_in, data_out, 
    addr, write, 
    valid_in, done,
    direction // for debug
);

// Parameter Declarations -------------------------------------
parameter DATA_WIDTH = 8;
parameter ADDR_WIDTH = 8;

// Interface Declarations -------------------------------------
input clk;
input rstn;

// sccb interface
output scl;
inout  sda;

// internal interface
input  [DATA_WIDTH - 1 : 0] data_in;
input  [ADDR_WIDTH - 1 : 0] addr;     // address to wirte or read
input  write;                         // 1 - write, 0 - read
input  valid_in;
output [DATA_WIDTH - 1 : 0] data_out; 
output done;

output direction; // for debug

// Reg and Wire Declarations ----------------------------------
// capture registers
reg [DATA_WIDTH - 1 : 0] data_in_r;
reg [ADDR_WIDTH - 1 : 0] addr_r;
reg write_r;

// handshake signals
reg ready;

// Seq Logic --------------------------------------------------
always @ (posedge clk or negedge rstn) begin
    if(!rstn) begin
        data_in_r <= 'b0;
        addr_r <= 'b0;
        write_r <= 'b0;
    end else begin
        if(valid_in == 1'b1 && ready == 1'b1) begin
            data_in_r <= data_in;
            addr_r <= addr;
            write_r <= write;
        end 
    end
end

always @ (posedge clk or negedge rstn) begin
    if(!rstn) ready <= 1'b1; 
    else begin
        if(valid_in == 1'b1) ready <= 1'b0;
        else if(done == 1'b1) ready <= 1'b1;
    end
end

// Sub Module Declarations ------------------------------------
sccb_fsm sccb_fsm(
    .clk(clk),
    .rstn(rstn),
    .valid_in(valid_in),
    .write(write_r),
    .data_in(data_in_r),
    .addr(addr_r),
    .done(done),
    .data_out(data_out),
    .scl(scl),
    .sda(sda),
    .direction(direction) // for debug
);

endmodule

testbench/sccb_tb.v
//////////////////////////////////////////////////////////////////////////////////
// Company: Private
// Engineer: JunkaiZhan
// 
// Create Date: 2018-12-17
// Design Name: Image Recognition
// Module Name: sccb interface driver for dcmi (for ov7725)
// Target Devices: ASIC/FPGA
// Tool Version: 
// Description: 
//      Testbench
// Dependencies: 
//      sccb.v
// Revision: 
// Revision 0.01 - File Created
//
////////////////////////////////////////////////////////////////////////////////////
`timescale 1ns/1ps

module sccb_tb();

// Parameter Declarations 
parameter DATA_WIDTH = 8;
parameter ADDR_WIDTH = 8;
parameter time_cycle = 10;

// Interface Declaration
reg clk, rstn;
reg [DATA_WIDTH - 1 : 0] data_in;
reg [ADDR_WIDTH - 1 : 0] addr;     // address to wirte or read
reg write;                         // 1 - write, 0 - read
reg valid_in;

wire sda, direction;
reg sda_out;
assign sda = !direction ? sda_out : 1'bz;

wire scl;
wire [DATA_WIDTH - 1 : 0] data_out; 
wire done; 

// Design Under Test
sccb dut(
    .clk(clk),
    .rstn(rstn),
    .data_in(data_in),
    .addr(addr),
    .write(write),
    .valid_in(valid_in),
    .sda(sda),
    .scl(scl),
    .data_out(data_out),
    .done(done),
    .direction(direction)
);

// clock and reset_n
initial begin
    clk = 1;
    rstn = 1;
    #(time_cycle*2) rstn = 0;
    #(time_cycle*2) rstn = 1;
end

always begin
    #(time_cycle/2) clk = ~clk;
end

// dump out file and variables
initial begin
    $dumpfile("sccb_wv.vcd");
    $dumpvars(0, dut);
end

// logic
initial begin
    data_in = 0;
    addr = 0;
    write = 0;
    valid_in = 0;
    sda_out = 1;
    #(time_cycle*6);

    // write command
    data_in = 8'h5b;
    addr = 8'ha6;
    write = 0;
    sda_out = 0;
    valid_in = 1;
    #time_cycle;
    data_in = 8'h5b;
    addr = 8'ha6;
    write = 0;
    valid_in = 0;
    sda_out = 0;
    #(time_cycle*100);

    // write command 2
    data_in = 8'h73;
    addr = 8'h95;
    write = 0;
    valid_in = 1;
    sda_out = 0;
    #time_cycle;
    data_in = 8'h73;
    addr = 8'h95;
    write = 0;
    valid_in = 0;
    sda_out = 0;
    #(time_cycle*100);

    // read command _ failed
    data_in = 8'h5b;
    addr = 8'ha6;
    write = 1;
    valid_in = 1;
    sda_out = 1;
    #time_cycle;
    data_in = 8'h5b;
    addr = 8'ha6;
    write = 1;
    valid_in = 0;
    sda_out = 1;
    #(time_cycle*100);

    // read command _ pass
    data_in = 8'h73;
    addr = 8'h95;
    write = 1;
    valid_in = 1;
    sda_out = 0;
    #time_cycle;
    data_in = 8'h73;
    addr = 8'h95;
    write = 1;
    valid_in = 0;
    sda_out = 0;
    #(time_cycle*100);

    #(time_cycle*100);
    $finish;
end

endmodule

sim/sccb_wv.vcd
$date
	Wed Dec 19 22:53:08 2018
$end
$version
	Icarus Verilog
$end
$timescale
	1ps
$end
$scope module sccb_tb $end
$scope module dut $end
$var wire 8 ! addr [7:0] $end
$var wire 1 " clk $end
$var wire 8 # data_in [7:0] $end
$var wire 1 $ rstn $end
$var wire 1 % sda $end
$var wire 1 & valid_in $end
$var wire 1 ' write $end
$var wire 1 ( scl $end
$var wire 1 ) done $end
$var wire 1 * direction $end
$var wire 8 + data_out [7:0] $end
$var reg 8 , addr_r [7:0] $end
$var reg 8 - data_in_r [7:0] $end
$var reg 1 . ready $end
$var reg 1 / write_r $end
$scope module sccb_fsm $end
$var wire 8 0 addr [7:0] $end
$var wire 1 " clk $end
$var wire 8 1 data_in [7:0] $end
$var wire 8 2 data_out [7:0] $end
$var wire 1 * direction $end
$var wire 1 3 in_sda $end
$var wire 1 $ rstn $end
$var wire 1 ( scl $end
$var wire 1 % sda $end
$var wire 1 & valid_in $end
$var wire 1 / write $end
$var wire 1 4 valid_bit $end
$var wire 1 5 rec_finish $end
$var wire 1 ) done $end
$var wire 1 6 byte_counter_is_zero $end
$var wire 1 7 bit_counter_is_zero $end
$var reg 1 8 ack_valid $end
$var reg 4 9 bit_counter [3:0] $end
$var reg 2 : byte_counter [1:0] $end
$var reg 8 ; data_receive [7:0] $end
$var reg 5 < next_state [4:0] $end
$var reg 1 = out_sda $end
$var reg 1 > read_command $end
$var reg 4 ? rec_counter [3:0] $end
$var reg 1 @ scl_r $end
$var reg 1 A sda_out_en $end
$var reg 24 B seq [23:0] $end
$var reg 5 C state [4:0] $end
$var reg 1 D write_command $end
$upscope $end
$upscope $end
$upscope $end
$enddefinitions $end
#0
$dumpvars
xD
bx C
bx B
xA
x@
bx ?
x>
x=
bx <
bx ;
bx :
bx 9
x8
x7
x6
x5
x4
x3
bx 2
bx 1
bx 0
x/
x.
bx -
bx ,
bx +
x*
x)
x(
0'
0&
x%
1$
b0 #
1"
b0 !
$end
#5000
0"
#10000
1"
#15000
0"
#20000
03
1%
1=
1*
1A
1(
1@
04
b0 <
0)
b0 C
17
b0 9
16
b0 :
b0 B
08
05
b0 ?
b0 +
b0 2
b0 ;
0D
0>
0/
b0 ,
b0 0
b0 -
b0 1
1.
1"
0$
#25000
0"
#30000
1"
#35000
0"
#40000
1"
1$
#45000
0"
#50000
1"
#55000
0"
#60000
b1 <
07
b1000 9
06
b10 :
1D
b10100110 ,
b10100110 0
b1011011 -
b1011011 1
0.
1"
1&
b10100110 !
b1011011 #
#65000
0"
#70000
0%
14
0=
b10 <
b100001001010011001011011 B
b1 C
1"
0&
#75000
0"
#80000
0(
0@
b11 <
b10 C
1"
#85000
0"
#90000
1%
1=
b100 <
b11 C
1"
#95000
0"
#100000
1(
1@
b101 <
b100 C
b111 9
1"
#105000
0"
#110000
0(
0@
b11 <
b101 C
1"
#115000
0"
#120000
0%
0=
b100 <
04
b11 C
b10010100110010110110 B
1"
#125000
0"
#130000
1(
1@
b101 <
b110 9
b100 C
1"
#135000
0"
#140000
0(
0@
b11 <
b101 C
1"
#145000
0"
#150000
b100 <
b100101001100101101100 B
b11 C
1"
#155000
0"
#160000
1(
1@
b101 <
b100 C
b101 9
1"
#165000
0"
#170000
0(
0@
b11 <
b101 C
1"
#175000
0"
#180000
b100 <
b11 C
b1001010011001011011000 B
1"
#185000
0"
#190000
1(
1@
b101 <
b100 9
b100 C
1"
#195000
0"
#200000
0(
0@
b11 <
b101 C
1"
#205000
0"
#210000
b100 <
b10010100110010110110000 B
b11 C
1"
#215000
0"
#220000
1(
1@
b101 <
b100 C
b11 9
1"
#225000
0"
#230000
0(
0@
b11 <
b101 C
1"
#235000
0"
#240000
1%
1=
b100 <
14
b11 C
b100101001100101101100000 B
1"
#245000
0"
#250000
1(
1@
b101 <
b10 9
b100 C
1"
#255000
0"
#260000
0(
0@
b11 <
b101 C
1"
#265000
0"
#270000
0%
0=
04
b100 <
b1010011001011011000000 B
b11 C
1"
#275000
0"
#280000
1(
1@
b101 <
b100 C
b1 9
1"
#285000
0"
#290000
0(
0@
b11 <
b101 C
1"
#295000
0"
#300000
b100 <
b11 C
b10100110010110110000000 B
1"
#305000
0"
#310000
1(
1@
b101 <
17
b0 9
b100 C
1"
#315000
0"
#320000
0(
0@
b110 <
b101 C
1"
#325000
0"
#330000
14
0*
0A
b111 <
b101001100101101100000000 B
b110 C
1"
#335000
0"
#340000
1(
1@
b1000 <
b111 C
18
1"
#345000
0"
#350000
0(
0@
b11 <
b1000 C
1"
#355000
0"
#360000
1%
1=
1*
1A
b100 <
b11 C
1"
#365000
0"
#370000
1(
1@
b101 <
b1 :
07
b111 9
b100 C
1"
#375000
0"
#380000
0(
0@
b11 <
b101 C
1"
#385000
0"
#390000
0%
0=
04
b100 <
b10011001011011000000000 B
b11 C
1"
#395000
0"
#400000
1(
1@
b101 <
b100 C
b110 9
1"
#405000
0"
#410000
0(
0@
b11 <
b101 C
1"
#415000
0"
#420000
1%
1=
b100 <
14
b11 C
b100110010110110000000000 B
1"
#425000
0"
#430000
1(
1@
b101 <
b101 9
b100 C
1"
#435000
0"
#440000
0(
0@
b11 <
b101 C
1"
#445000
0"
#450000
0%
0=
04
b100 <
b1100101101100000000000 B
b11 C
1"
#455000
0"
#460000
1(
1@
b101 <
b100 C
b100 9
1"
#465000
0"
#470000
0(
0@
b11 <
b101 C
1"
#475000
0"
#480000
b100 <
b11 C
b11001011011000000000000 B
1"
#485000
0"
#490000
1(
1@
b101 <
b11 9
b100 C
1"
#495000
0"
#500000
0(
0@
b11 <
b101 C
1"
#505000
0"
#510000
1%
1=
14
b100 <
b110010110110000000000000 B
b11 C
1"
#515000
0"
#520000
1(
1@
b101 <
b100 C
b10 9
1"
#525000
0"
#530000
0(
0@
b11 <
b101 C
1"
#535000
0"
#540000
b100 <
b11 C
b100101101100000000000000 B
1"
#545000
0"
#550000
1(
1@
b101 <
b1 9
b100 C
1"
#555000
0"
#560000
0(
0@
b11 <
b101 C
1"
#565000
0"
#570000
0%
0=
04
b100 <
b1011011000000000000000 B
b11 C
1"
#575000
0"
#580000
1(
1@
b101 <
b100 C
17
b0 9
1"
#585000
0"
#590000
0(
0@
b110 <
b101 C
1"
#595000
0"
#600000
0*
0A
b111 <
b110 C
b10110110000000000000000 B
1"
#605000
0"
#610000
1(
1@
b1000 <
b111 C
1"
#615000
0"
#620000
0(
0@
b11 <
b1000 C
1"
#625000
0"
#630000
0%
1*
1A
b100 <
b11 C
1"
#635000
0"
#640000
1(
1@
b101 <
b100 C
16
b0 :
07
b111 9
1"
#645000
0"
#650000
0(
0@
b11 <
b101 C
1"
#655000
0"
#660000
1%
1=
b100 <
14
b11 C
b101101100000000000000000 B
1"
#665000
0"
#670000
1(
1@
b101 <
b110 9
b100 C
1"
#675000
0"
#680000
0(
0@
b11 <
b101 C
1"
#685000
0"
#690000
0%
0=
04
b100 <
b11011000000000000000000 B
b11 C
1"
#695000
0"
#700000
1(
1@
b101 <
b100 C
b101 9
1"
#705000
0"
#710000
0(
0@
b11 <
b101 C
1"
#715000
0"
#720000
1%
1=
b100 <
14
b11 C
b110110000000000000000000 B
1"
#725000
0"
#730000
1(
1@
b101 <
b100 9
b100 C
1"
#735000
0"
#740000
0(
0@
b11 <
b101 C
1"
#745000
0"
#750000
b100 <
b101100000000000000000000 B
b11 C
1"
#755000
0"
#760000
1(
1@
b101 <
b100 C
b11 9
1"
#765000
0"
#770000
0(
0@
b11 <
b101 C
1"
#775000
0"
#780000
0%
0=
b100 <
04
b11 C
b11000000000000000000000 B
1"
#785000
0"
#790000
1(
1@
b101 <
b10 9
b100 C
1"
#795000
0"
#800000
0(
0@
b11 <
b101 C
1"
#805000
0"
#810000
1%
1=
14
b100 <
b110000000000000000000000 B
b11 C
1"
#815000
0"
#820000
1(
1@
b101 <
b100 C
b1 9
1"
#825000
0"
#830000
0(
0@
b11 <
b101 C
1"
#835000
0"
#840000
b100 <
b11 C
b100000000000000000000000 B
1"
#845000
0"
#850000
1(
1@
b101 <
17
b0 9
b100 C
1"
#855000
0"
#860000
0(
0@
b110 <
b101 C
1"
#865000
0"
#870000
0%
04
0*
0A
b111 <
b0 B
b110 C
1"
#875000
0"
#880000
1(
1@
b1000 <
b111 C
1"
#885000
0"
#890000
0(
0@
b1111 <
b1000 C
1"
#895000
0"
#900000
0%
0=
1*
1A
b10000 <
b1111 C
1"
#905000
0"
#910000
1(
1@
b10001 <
b10000 C
1"
#915000
0"
#920000
1%
1=
b0 <
1)
b10001 C
1"
#925000
0"
#930000
1.
0D
0)
b0 C
1"
#935000
0"
#940000
1"
#945000
0"
#950000
1"
#955000
0"
#960000
1"
#965000
0"
#970000
1"
#975000
0"
#980000
1"
#985000
0"
#990000
1"
#995000
0"
#1000000
1"
#1005000
0"
#1010000
1"
#1015000
0"
#1020000
1"
#1025000
0"
#1030000
1"
#1035000
0"
#1040000
1"
#1045000
0"
#1050000
1"
#1055000
0"
#1060000
1"
#1065000
0"
#1070000
b1 <
0.
b10010101 ,
b10010101 0
b1110011 -
b1110011 1
1D
07
b1000 9
06
b10 :
1"
1&
b10010101 !
b1110011 #
#1075000
0"
#1080000
0%
0=
b10 <
14
b1 C
b100001001001010101110011 B
1"
0&
#1085000
0"
#1090000
0(
0@
b11 <
b10 C
1"
#1095000
0"
#1100000
1%
1=
b100 <
b11 C
1"
#1105000
0"
#1110000
1(
1@
b101 <
b111 9
b100 C
1"
#1115000
0"
#1120000
0(
0@
b11 <
b101 C
1"
#1125000
0"
#1130000
0%
0=
04
b100 <
b10010010101011100110 B
b11 C
1"
#1135000
0"
#1140000
1(
1@
b101 <
b100 C
b110 9
1"
#1145000
0"
#1150000
0(
0@
b11 <
b101 C
1"
#1155000
0"
#1160000
b100 <
b11 C
b100100101010111001100 B
1"
#1165000
0"
#1170000
1(
1@
b101 <
b101 9
b100 C
1"
#1175000
0"
#1180000
0(
0@
b11 <
b101 C
1"
#1185000
0"
#1190000
b100 <
b1001001010101110011000 B
b11 C
1"
#1195000
0"
#1200000
1(
1@
b101 <
b100 C
b100 9
1"
#1205000
0"
#1210000
0(
0@
b11 <
b101 C
1"
#1215000
0"
#1220000
b100 <
b11 C
b10010010101011100110000 B
1"
#1225000
0"
#1230000
1(
1@
b101 <
b11 9
b100 C
1"
#1235000
0"
#1240000
0(
0@
b11 <
b101 C
1"
#1245000
0"
#1250000
1%
1=
14
b100 <
b100100101010111001100000 B
b11 C
1"
#1255000
0"
#1260000
1(
1@
b101 <
b100 C
b10 9
1"
#1265000
0"
#1270000
0(
0@
b11 <
b101 C
1"
#1275000
0"
#1280000
0%
0=
b100 <
04
b11 C
b1001010101110011000000 B
1"
#1285000
0"
#1290000
1(
1@
b101 <
b1 9
b100 C
1"
#1295000
0"
#1300000
0(
0@
b11 <
b101 C
1"
#1305000
0"
#1310000
b100 <
b10010101011100110000000 B
b11 C
1"
#1315000
0"
#1320000
1(
1@
b101 <
b100 C
17
b0 9
1"
#1325000
0"
#1330000
0(
0@
b110 <
b101 C
1"
#1335000
0"
#1340000
0*
0A
b111 <
14
b110 C
b100101010111001100000000 B
1"
#1345000
0"
#1350000
1(
1@
b1000 <
b111 C
1"
#1355000
0"
#1360000
0(
0@
b11 <
b1000 C
1"
#1365000
0"
#1370000
1%
1=
1*
1A
b100 <
b11 C
1"
#1375000
0"
#1380000
1(
1@
b101 <
b100 C
b1 :
07
b111 9
1"
#1385000
0"
#1390000
0(
0@
b11 <
b101 C
1"
#1395000
0"
#1400000
0%
0=
b100 <
04
b11 C
b1010101110011000000000 B
1"
#1405000
0"
#1410000
1(
1@
b101 <
b110 9
b100 C
1"
#1415000
0"
#1420000
0(
0@
b11 <
b101 C
1"
#1425000
0"
#1430000
b100 <
b10101011100110000000000 B
b11 C
1"
#1435000
0"
#1440000
1(
1@
b101 <
b100 C
b101 9
1"
#1445000
0"
#1450000
0(
0@
b11 <
b101 C
1"
#1455000
0"
#1460000
1%
1=
b100 <
14
b11 C
b101010111001100000000000 B
1"
#1465000
0"
#1470000
1(
1@
b101 <
b100 9
b100 C
1"
#1475000
0"
#1480000
0(
0@
b11 <
b101 C
1"
#1485000
0"
#1490000
0%
0=
04
b100 <
b10101110011000000000000 B
b11 C
1"
#1495000
0"
#1500000
1(
1@
b101 <
b100 C
b11 9
1"
#1505000
0"
#1510000
0(
0@
b11 <
b101 C
1"
#1515000
0"
#1520000
1%
1=
b100 <
14
b11 C
b101011100110000000000000 B
1"
#1525000
0"
#1530000
1(
1@
b101 <
b10 9
b100 C
1"
#1535000
0"
#1540000
0(
0@
b11 <
b101 C
1"
#1545000
0"
#1550000
0%
0=
04
b100 <
b10111001100000000000000 B
b11 C
1"
#1555000
0"
#1560000
1(
1@
b101 <
b100 C
b1 9
1"
#1565000
0"
#1570000
0(
0@
b11 <
b101 C
1"
#1575000
0"
#1580000
1%
1=
b100 <
14
b11 C
b101110011000000000000000 B
1"
#1585000
0"
#1590000
1(
1@
b101 <
17
b0 9
b100 C
1"
#1595000
0"
#1600000
0(
0@
b110 <
b101 C
1"
#1605000
0"
#1610000
0%
04
0*
0A
b111 <
b11100110000000000000000 B
b110 C
1"
#1615000
0"
#1620000
1(
1@
b1000 <
b111 C
1"
#1625000
0"
#1630000
0(
0@
b11 <
b1000 C
1"
#1635000
0"
#1640000
0%
0=
1*
1A
b100 <
b11 C
1"
#1645000
0"
#1650000
1(
1@
b101 <
16
b0 :
07
b111 9
b100 C
1"
#1655000
0"
#1660000
0(
0@
b11 <
b101 C
1"
#1665000
0"
#1670000
1%
1=
14
b100 <
b111001100000000000000000 B
b11 C
1"
#1675000
0"
#1680000
1(
1@
b101 <
b100 C
b110 9
1"
#1685000
0"
#1690000
0(
0@
b11 <
b101 C
1"
#1695000
0"
#1700000
b100 <
b11 C
b110011000000000000000000 B
1"
#1705000
0"
#1710000
1(
1@
b101 <
b101 9
b100 C
1"
#1715000
0"
#1720000
0(
0@
b11 <
b101 C
1"
#1725000
0"
#1730000
b100 <
b100110000000000000000000 B
b11 C
1"
#1735000
0"
#1740000
1(
1@
b101 <
b100 C
b100 9
1"
#1745000
0"
#1750000
0(
0@
b11 <
b101 C
1"
#1755000
0"
#1760000
0%
0=
b100 <
04
b11 C
b1100000000000000000000 B
1"
#1765000
0"
#1770000
1(
1@
b101 <
b11 9
b100 C
1"
#1775000
0"
#1780000
0(
0@
b11 <
b101 C
1"
#1785000
0"
#1790000
b100 <
b11000000000000000000000 B
b11 C
1"
#1795000
0"
#1800000
1(
1@
b101 <
b100 C
b10 9
1"
#1805000
0"
#1810000
0(
0@
b11 <
b101 C
1"
#1815000
0"
#1820000
1%
1=
b100 <
14
b11 C
b110000000000000000000000 B
1"
#1825000
0"
#1830000
1(
1@
b101 <
b1 9
b100 C
1"
#1835000
0"
#1840000
0(
0@
b11 <
b101 C
1"
#1845000
0"
#1850000
b100 <
b100000000000000000000000 B
b11 C
1"
#1855000
0"
#1860000
1(
1@
b101 <
b100 C
17
b0 9
1"
#1865000
0"
#1870000
0(
0@
b110 <
b101 C
1"
#1875000
0"
#1880000
0%
0*
0A
b111 <
04
b110 C
b0 B
1"
#1885000
0"
#1890000
1(
1@
b1000 <
b111 C
1"
#1895000
0"
#1900000
0(
0@
b1111 <
b1000 C
1"
#1905000
0"
#1910000
0%
0=
1*
1A
b10000 <
b1111 C
1"
#1915000
0"
#1920000
1(
1@
b10001 <
b10000 C
1"
#1925000
0"
#1930000
1%
1=
b0 <
1)
b10001 C
1"
#1935000
0"
#1940000
0)
b0 C
0D
1.
1"
#1945000
0"
#1950000
1"
#1955000
0"
#1960000
1"
#1965000
0"
#1970000
1"
#1975000
0"
#1980000
1"
#1985000
0"
#1990000
1"
#1995000
0"
#2000000
1"
#2005000
0"
#2010000
1"
#2015000
0"
#2020000
1"
#2025000
0"
#2030000
1"
#2035000
0"
#2040000
1"
#2045000
0"
#2050000
1"
#2055000
0"
#2060000
1"
#2065000
0"
#2070000
1"
#2075000
0"
#2080000
b1 <
07
b1000 9
06
b10 :
1D
1/
b10100110 ,
b10100110 0
b1011011 -
b1011011 1
0.
1"
1&
1'
b10100110 !
b1011011 #
#2085000
0"
#2090000
0%
14
0=
b10 <
b100001001010011001011011 B
b1 C
1"
0&
#2095000
0"
#2100000
0(
0@
b11 <
b10 C
1"
#2105000
0"
#2110000
1%
1=
b100 <
b11 C
1"
#2115000
0"
#2120000
1(
1@
b101 <
b100 C
b111 9
1"
#2125000
0"
#2130000
0(
0@
b11 <
b101 C
1"
#2135000
0"
#2140000
0%
0=
b100 <
04
b11 C
b10010100110010110110 B
1"
#2145000
0"
#2150000
1(
1@
b101 <
b110 9
b100 C
1"
#2155000
0"
#2160000
0(
0@
b11 <
b101 C
1"
#2165000
0"
#2170000
b100 <
b100101001100101101100 B
b11 C
1"
#2175000
0"
#2180000
1(
1@
b101 <
b100 C
b101 9
1"
#2185000
0"
#2190000
0(
0@
b11 <
b101 C
1"
#2195000
0"
#2200000
b100 <
b11 C
b1001010011001011011000 B
1"
#2205000
0"
#2210000
1(
1@
b101 <
b100 9
b100 C
1"
#2215000
0"
#2220000
0(
0@
b11 <
b101 C
1"
#2225000
0"
